jdformvalidator/__init__.py
jdformvalidator/validators.py
jdformvalidator-1.0.0.dist-info/licenses/LICENSE
jdformvalidator-1.0.0.dist-info/METADATA
jdformvalidator-1.0.0.dist-info/WHEEL
jdformvalidator-1.0.0.dist-info/top_level.txt
jdformvalidator-1.0.0.dist-info/RECORD
