Metadata-Version: 2.4
Name: jdformvalidator
Version: 1.0.0
Summary: JD Form Validator - A Professional Python Library for Input Validations
Home-page: https://github.com/jalal2303/jdformvalidator
Author: Jalaludheen H (JD)
Author-email: jalaludheen2303@gmail.com
Keywords: validation,form,email,phone,python,pan,aadhaar,file type,dob
Classifier: Programming Language :: Python :: 3
Classifier: License :: OSI Approved :: MIT License
Classifier: Operating System :: OS Independent
Classifier: Intended Audience :: Developers
Classifier: Topic :: Software Development :: Libraries :: Python Modules
Requires-Python: >=3.6
License-File: LICENSE
Dynamic: author
Dynamic: author-email
Dynamic: classifier
Dynamic: description
Dynamic: description-content-type
Dynamic: home-page
Dynamic: keywords
Dynamic: license-file
Dynamic: requires-python
Dynamic: summary
